betting_models/__init__.py
betting_models/core/__init__.py
betting_models/core/allocation.py
betting_models/core/base_generator.py
betting_models/football/league_markets/__init__.py
betting_models/football/league_markets/seed.py
betting_models/football/match_markets/__init__.py
betting_models/football/match_markets/backsolve_lambda.py
betting_models/football/match_markets/config.py
betting_models/football/match_markets/formats.py
betting_models/football/match_markets/market_model_base.py
betting_models/football/match_markets/score_model.py
betting_models/football/match_markets/seed.py
betting_models/generic/seed.py
betting_models/racing/__init__.py
betting_models/racing/seed.py
betting_models-0.1.6.dist-info/WHEEL
betting_models-0.1.6.dist-info/METADATA
betting_models-0.1.6.dist-info/RECORD
