Metadata-Version: 2.1
Name: betting-models
Version: 0.1.6
Summary: Statistical tools for highly exotic betting markets.
License: Apache-2.0
Author: Michael Watson
Requires-Python: >=3.8.0,<3.9.0
Classifier: License :: OSI Approved :: Apache Software License
Classifier: Programming Language :: Python :: 3
Classifier: Programming Language :: Python :: 3.8
Requires-Dist: matplotlib (>=3.5.1,<4.0.0)
Requires-Dist: numpy (>=1.22.2,<2.0.0)
Requires-Dist: pandas (>=1.4.1,<2.0.0)
Requires-Dist: scipy (>=1.8.0,<2.0.0)
Requires-Dist: seaborn (>=0.11.2,<0.12.0)
